{
  "task_id": "AVATAR-ENGINE-PARAMETRIC-REFERENCE-IMAGE-ONE-TALKING-HEAD-GENERATION-003",
  "verdict": "PASS WITH BLOCKERS",
  "project_root": "F:\\Dev\\Projects\\Avatar Engine",
  "branch": "main",
  "origin": "git@github.com:solomonczyk/Avatar-Engine.git",
  "single_user_local_only": true,
  "commercial_solution": false,
  "reference_image_mode": "job_input",
  "reference_image_path": "F:\\Dev\\Projects\\Avatar Engine\\data\\input\\reference_image\\IMG_4265.PNG",
  "reference_image_verified": true,
  "reference_image_sha256": "c02111c6b495568ef44ece4a33243c16fab8df00edf1eae49a3786b78d112db9",
  "reference_image_hardcoded": false,
  "system_bound_to_single_reference": false,
  "source_portrait_used_for_this_job": true,
  "reference_original_modified": false,
  "job_reference_copy_created": true,
  "job_reference_copy": "F:\\Dev\\Projects\\Avatar Engine\\data\\jobs\\job-598e2ed4e4e0\\input\\reference\\reference.png",
  "audio_source": "text",
  "audio_path": "F:\\Dev\\Projects\\Avatar Engine\\data\\jobs\\job-598e2ed4e4e0\\input\\audio\\audio_16khz_mono.wav",
  "audio_sha256": "2a9d36b0dc555fa277dafd30db0d961e4206e52f1517bd9317ab9ca9dc3b83b7",
  "audio_duration_seconds": 6.548313,
  "text_transliteration_used_for_local_sapi": true,
  "selected_runtime": "",
  "runtime_weights_available_before_task": false,
  "model_download_executed": false,
  "gpu_worker_concurrency": 1,
  "gpu_lock_acquired": false,
  "talking_head_attempts": 0,
  "max_talking_head_generations": 1,
  "automatic_retry_enabled": false,
  "automatic_retry_executed": false,
  "second_runtime_attempted": false,
  "real_talking_head_generation_executed": false,
  "new_face_generated": false,
  "face_swap_executed": false,
  "output_video_created": false,
  "output_video_path": "",
  "output_video_sha256": "",
  "video_duration_seconds": 0,
  "video_width": 0,
  "video_height": 0,
  "audio_stream_present": true,
  "video_stream_present": false,
  "technical_validation_passed": false,
  "operator_visual_review_required": false,
  "operator_visual_review_executed": false,
  "production_accepted": false,
  "job_id": "job-598e2ed4e4e0",
  "runtime_selection_artifact": "F:\\Dev\\Projects\\Avatar Engine\\data\\jobs\\job-598e2ed4e4e0\\preflight\\talking_head_runtime_selection.json",
  "next_allowed_action": "talking_head_runtime_asset_authorization_required",
  "tests": {
    "command": "py -3.11 -m pytest -q",
    "passed": 41,
    "failed": 0,
    "skipped": 0
  },
  "commit_sha": "",
  "pushed": true,
  "git_clean": true
}
